[
       {
              "name": "Northwest",
              "isActive": "no",
              "command": "retreat northwest",
              "script": "",
              "keys": "keypad+home",
              "isFolder": "no"
       },
       {
              "name": "North",
              "isActive": "no",
              "command": "retreat north",
              "script": "",
              "keys": "keypad+up",
              "isFolder": "no"
       },
       {
              "name": "Northeast",
              "isActive": "no",
              "command": "retreat northeast",
              "script": "",
              "keys": "keypad+pgup",
              "isFolder": "no"
       },
       {
              "name": "West",
              "isActive": "no",
              "command": "retreat west",
              "script": "",
              "keys": "keypad+left",
              "isFolder": "no"
       },
       {
              "name": "East",
              "isActive": "no",
              "command": "retreat east",
              "script": "",
              "keys": "keypad+right",
              "isFolder": "no"
       },
       {
              "name": "Southwest",
              "isActive": "no",
              "command": "retreat southwest",
              "script": "",
              "keys": "keypad+end",
              "isFolder": "no"
       },
       {
              "name": "South",
              "isActive": "no",
              "command": "retreat south",
              "script": "",
              "keys": "keypad+down",
              "isFolder": "no"
       },
       {
              "name": "Southeast",
              "isActive": "no",
              "command": "retreat southeast",
              "script": "",
              "keys": "keypad+pgdn",
              "isFolder": "no"
       },
       {
              "name": "Down",
              "isActive": "no",
              "command": "retreat down",
              "script": "",
              "keys": "shift+keypad+minus",
              "isFolder": "no"
       },
       {
              "name": "Up",
              "isActive": "no",
              "command": "retreat up",
              "script": "",
              "keys": "shift+keypad+plus",
              "isFolder": "no"
       }
]
